rhinoWrapper/__init__.py
rhinoWrapper/__rhinoWrapper.py
rhinoWrapper-0.1.1.dist-info/METADATA
rhinoWrapper-0.1.1.dist-info/RECORD
rhinoWrapper-0.1.1.dist-info/WHEEL
rhinoWrapper-0.1.1.dist-info/metadata.json
rhinoWrapper-0.1.1.dist-info/top_level.txt
