Metadata-Version: 2.0
Name: rhinoWrapper
Version: 0.1.1
Summary: 최석재 선생님의 RHINO 형태소분석기를 사용하기 좋게 덧씌운 래퍼 클래스입니다. 
Home-page: https://github.com/INGPlay
Author: 김병주
Author-email: atker14@gmail.com
Classifier: Programming Language :: Python :: 3
Classifier: License :: OSI Approved :: MIT License
Classifier: Operating System :: OS Independent
Requires-Python: >=3
License-File: LICENSE
Requires-Dist: JPype1
Requires-Dist: rhinoMorph
